Workbook

Sheet Orçamento_Janeiro
A1: ORÇAMENTO DOMÉSTICO
B2: RENDA FAMILIAR | C2: 5500
B3: GASTOS TOTAIS | C3: =SUM(C17,F17,I17,L17,O17,R17,U17,X17) -> 5120
B4: SALDO DO MÊS | C4: =C2-C3 -> 380
A6: Moradia | D6: Saúde | G6: Alimentação | J6: Transporte | M6: Vestuário | P6: Educação | S6: Lazer | V6: Investimento
A7: Custo | D7: Custo | G7: Custo | J7: Custo | M7: Custo | P7: Custo | S7: Custo | V7: Custo
A8: 1 | B8: Aluguel | C8: 900 | D8: 1 | E8: Remédios | F8: 200 | G8: 1 | H8: Supermercado | I8: 700 | J8: 1 | K8: Transporte Público | M8: 1 | N8: Roupas | O8: 200 | P8: 1 | Q8: Mensalidade/Universidade | R8: 1000 | S8: 1 | T8: Passeios | U8: 150 | V8: 1 | W8: Poupança | X8: 100
A9: 2 | B9: Condomínio | C9: 0 | D9: 2 | E9: Plano de Saúde | G9: 2 | H9: Feira | I9: 150 | J9: 2 | K9: Carro/Combustível | L9: 270 | M9: 2 | N9: Calçados | O9: 200 | P9: 2 | Q9: Material Escolar | R9: 500 | S9: 2 | T9: Viagens
A10: 3 | B10: Celular | C10: 80 | D10: 3 | E10: Consulta médica | G10: 3 | H10: Açougue | J10: 3 | K10: IPVA
A11: 4 | B11: Luz | C11: 120 | D11: 4 | E11: Exame
A12: 5 | B12: Gás | C12: 110 | D12: 5 | E12: Dentista
A13: 6 | B13: Água/esgoto | C13: 80
A14: 7 | B14: Internet | C14: 100
A15: 8 | B15: Serviços de Streaming | C15: 60
A16: 9 | B16: IPTU | C16: 200
B17: SUBTOTAL | C17: =SUM(C8:C16) -> 1650 | E17: SUBTOTAL | F17: =SUM(F8:F16) -> 200 | H17: SUBTOTAL | I17: =SUM(I8:I16) -> 850 | K17: SUBTOTAL | L17: =SUM(L8:L16) -> 270 | N17: SUBTOTAL | O17: =SUM(O8:O16) -> 400 | Q17: SUBTOTAL | R17: =SUM(R8:R16) -> 1500 | T17: SUBTOTAL | U17: =SUM(U8:U16) -> 150 | W17: SUBTOTAL | X17: =SUM(X8:X16) -> 100
B21: GASTOS TOTAIS | C21: CUSTO
B22: Moradia | C22: =C17 -> 1650
B23: Saúde | C23: =F17 -> 200
B24: Alimentação | C24: =I17 -> 850
B25: Transporte | C25: =L17 -> 270
B26: Vestuário | C26: =O17 -> 400
B27: Educação | C27: =R17 -> 1500
B28: Lazer | C28: =U17 -> 150
B29: Investimentos | C29: =X17 -> 100

Sheet Orçamento_Fevereiro
A1: ORÇAMENTO DOMÉSTICO
B2: RENDA FAMILIAR | C2: 5500
B3: GASTOS TOTAIS | C3: =SUM(C17,F17,I17,L17,O17,R17,U17,X17) -> 3850
B4: SALDO DO MÊS | C4: =C2-C3 -> 1650
A6: Moradia | D6: Saúde | G6: Alimentação | J6: Transporte | M6: Vestuário | P6: Educação | S6: Lazer | V6: Investimento
A7: Custo | D7: Custo | G7: Custo | J7: Custo | M7: Custo | P7: Custo | S7: Custo | V7: Custo
A8: 1 | B8: Aluguel | C8: 900 | D8: 1 | E8: Remédios | F8: 50 | G8: 1 | H8: Supermercado | I8: 500 | J8: 1 | K8: Transporte Público | M8: 1 | N8: Roupas | O8: 80 | P8: 1 | Q8: Mensalidade/Universidade | R8: 1000 | S8: 1 | T8: Passeios | U8: 50 | V8: 1 | W8: Poupança | X8: 100
A9: 2 | B9: Condomínio | C9: 0 | D9: 2 | E9: Plano de Saúde | G9: 2 | H9: Feira | I9: 150 | J9: 2 | K9: Carro/Combustível | L9: 270 | M9: 2 | N9: Calçados | O9: 0 | P9: 2 | Q9: Material Escolar | R9: 0 | S9: 2 | T9: Viagens
A10: 3 | B10: Celular | C10: 80 | D10: 3 | E10: Consulta médica | G10: 3 | H10: Açougue | J10: 3 | K10: IPVA
A11: 4 | B11: Luz | C11: 120 | D11: 4 | E11: Exame
A12: 5 | B12: Gás | C12: 110 | D12: 5 | E12: Dentista
A13: 6 | B13: Água/esgoto | C13: 80
A14: 7 | B14: Internet | C14: 100
A15: 8 | B15: Serviços de Streaming | C15: 60
A16: 9 | B16: IPTU | C16: 200
B17: SUBTOTAL | C17: =SUM(C8:C16) -> 1650 | E17: SUBTOTAL | F17: =SUM(F8:F16) -> 50 | H17: SUBTOTAL | I17: =SUM(I8:I16) -> 650 | K17: SUBTOTAL | L17: =SUM(L8:L16) -> 270 | N17: SUBTOTAL | O17: =SUM(O8:O16) -> 80 | Q17: SUBTOTAL | R17: =SUM(R8:R16) -> 1000 | T17: SUBTOTAL | U17: =SUM(U8:U16) -> 50 | W17: SUBTOTAL | X17: =SUM(X8:X16) -> 100

Sheet Orçamento_Março
A1: ORÇAMENTO DOMÉSTICO
B2: RENDA FAMILIAR | C2: 5500
B3: GASTOS TOTAIS | C3: =SUM(C17,F17,I17,L17,O17,R17,U17,X17) -> 3990
B4: SALDO DO MÊS | C4: =C2-C3 -> 1510
A6: Moradia | D6: Saúde | G6: Alimentação | J6: Transporte | M6: Vestuário | P6: Educação | S6: Lazer | V6: Investimento
A7: Custo | D7: Custo | G7: Custo | J7: Custo | M7: Custo | P7: Custo | S7: Custo | V7: Custo
A8: 1 | B8: Aluguel | C8: 900 | D8: 1 | E8: Remédios | F8: 120 | G8: 1 | H8: Supermercado | I8: 550 | J8: 1 | K8: Transporte Público | M8: 1 | N8: Roupas | O8: 40 | P8: 1 | Q8: Mensalidade/Universidade | R8: 1000 | S8: 1 | T8: Passeios | U8: 50 | V8: 1 | W8: Poupança | X8: 100
A9: 2 | B9: Condomínio | C9: 0 | D9: 2 | E9: Plano de Saúde | G9: 2 | H9: Feira | I9: 150 | J9: 2 | K9: Carro/Combustível | L9: 270 | M9: 2 | N9: Calçados | O9: 60 | P9: 2 | Q9: Material Escolar | R9: 0 | S9: 2 | T9: Viagens
A10: 3 | B10: Celular | C10: 80 | D10: 3 | E10: Consulta médica | G10: 3 | H10: Açougue | J10: 3 | K10: IPVA
A11: 4 | B11: Luz | C11: 120 | D11: 4 | E11: Exame
A12: 5 | B12: Gás | C12: 110 | D12: 5 | E12: Dentista
A13: 6 | B13: Água/esgoto | C13: 80
A14: 7 | B14: Internet | C14: 100
A15: 8 | B15: Serviços de Streaming | C15: 60
A16: 9 | B16: IPTU | C16: 200
B17: SUBTOTAL | C17: =SUM(C8:C16) -> 1650 | E17: SUBTOTAL | F17: =SUM(F8:F16) -> 120 | H17: SUBTOTAL | I17: =SUM(I8:I16) -> 700 | K17: SUBTOTAL | L17: =SUM(L8:L16) -> 270 | N17: SUBTOTAL | O17: =SUM(O8:O16) -> 100 | Q17: SUBTOTAL | R17: =SUM(R8:R16) -> 1000 | T17: SUBTOTAL | U17: =SUM(U8:U16) -> 50 | W17: SUBTOTAL | X17: =SUM(X8:X16) -> 100

Sheet Total_Geral_Trimestral
A1: Categoria | B1: JANEIRO | C1: FEVEREIRO | D1: MARÇO | E1: TOTAL GERAL | F1: MÉDIA GERAL
A2: Alimentação | B2: =Orçamento_Janeiro!I17 -> 850 | C2: =Orçamento_Fevereiro!I17 -> 650 | D2: =Orçamento_Março!I17 -> 700 | E2: =SUM(B2:D2) -> 2200 | F2: =AVERAGE(B2:D2) -> 733.33333
A3: Educação | B3: =Orçamento_Janeiro!R17 -> 1500 | C3: =Orçamento_Fevereiro!R17 -> 1000 | D3: =Orçamento_Março!R17 -> 1000 | E3: =SUM(B3:D3) -> 3500 | F3: =AVERAGE(B3:D3) -> 1166.6667
A4: Investimentos | B4: =Orçamento_Janeiro!X17 -> 100 | C4: =Orçamento_Fevereiro!X17 -> 100 | D4: =Orçamento_Março!X17 -> 100 | E4: =SUM(B4:D4) -> 300 | F4: =AVERAGE(B4:D4) -> 100
A5: Lazer | B5: =Orçamento_Janeiro!U17 -> 150 | C5: =Orçamento_Fevereiro!U17 -> 50 | D5: =Orçamento_Março!U17 -> 50 | E5: =SUM(B5:D5) -> 250 | F5: =AVERAGE(B5:D5) -> 83.333333
A6: Moradia | B6: =Orçamento_Janeiro!C17 -> 1650 | C6: =Orçamento_Fevereiro!C17 -> 1650 | D6: =Orçamento_Março!C17 -> 1650 | E6: =SUM(B6:D6) -> 4950 | F6: =AVERAGE(B6:D6) -> 1650
A7: Saúde | B7: =Orçamento_Janeiro!F17 -> 200 | C7: =Orçamento_Fevereiro!F17 -> 50 | D7: =Orçamento_Março!F17 -> 120 | E7: =SUM(B7:D7) -> 370 | F7: =AVERAGE(B7:D7) -> 123.33333
A8: Transporte | B8: =Orçamento_Janeiro!L17 -> 270 | C8: =Orçamento_Fevereiro!L17 -> 270 | D8: =Orçamento_Março!L17 -> 270 | E8: =SUM(B8:D8) -> 810 | F8: =AVERAGE(B8:D8) -> 270
A9: Vestuário | B9: =Orçamento_Janeiro!O17 -> 400 | C9: =Orçamento_Fevereiro!O17 -> 80 | D9: =Orçamento_Março!O17 -> 100 | E9: =SUM(B9:D9) -> 580 | F9: =AVERAGE(B9:D9) -> 193.33333
A10: TOTAL GERAL | B10: =SUM(B2:B9) -> 5120 | C10: =SUM(C2:C9) -> 3850 | D10: =SUM(D2:D9) -> 3990 | E10: =SUM(B10:D10) -> 12960 | F10: =SUM(F2:F9) -> 4320
F11: =MAX(F2:F9) -> 1650
F12: =MIN(F2:F9) -> 83.333333

Sheet Plan3
